Metadata-Version: 1.1
Name: jsonderef
Version: 1.0.0
Summary: A json dereferencing tool.
Home-page: https://github.com/apiwatcher/jsonderef
Author: Karel Jakubec
Author-email: karel@jakubec.name
License: MIT
Keywords: json ref reference dereference schema jsonschema
Platform: UNKNOWN
Classifier: Development Status :: 5 - Production/Stable
Classifier: Intended Audience :: Developers
Classifier: Topic :: Software Development :: Libraries :: Python Modules
Classifier: Topic :: Software Development :: Libraries
Classifier: License :: OSI Approved :: MIT License
Classifier: Programming Language :: Python :: 2
Classifier: Programming Language :: Python :: 2.7
